featimp/__init__.py
featimp/base.py
featimp-0.1.7.dist-info/LICENSE
featimp-0.1.7.dist-info/METADATA
featimp-0.1.7.dist-info/WHEEL
featimp-0.1.7.dist-info/top_level.txt
featimp-0.1.7.dist-info/RECORD
