Metadata-Version: 2.1
Name: featimp
Version: 0.1.7
Summary: Feature importance for machine learning
Home-page: https://github.com/Hasan-Basri-Akcay/featimp
Author: Hasan Basri Akcay
Author-email: hasan.basri.akcay@gmail.com
Keywords: python,data science,data analysis,exploratory data analysis,feature importance,beginner
Classifier: Programming Language :: Python :: 3
Classifier: Programming Language :: Python :: 2
Classifier: License :: OSI Approved :: MIT License
Classifier: Operating System :: OS Independent
License-File: LICENSE
Requires-Dist: pandas
Requires-Dist: numpy
Requires-Dist: matplotlib
Requires-Dist: seaborn
Requires-Dist: scikit-learn
Requires-Dist: lightgbm
Requires-Dist: catboost
Requires-Dist: scipy
